warn/.__init__.py.swp
warn/.__init__.py.un~
warn/.warn.py.un~
warn/__init__.py
warn/warn.py
warn-0.0.1.dist-info/WHEEL
warn-0.0.1.dist-info/METADATA
warn-0.0.1.dist-info/RECORD
