Metadata-Version: 1.2
Name: warn
Version: 0.0.1
Summary: A more flexible warning module. 
Home-page: https://github.com/Carreau/warn
License: UNKNOWN
Author: Matthias Bussonnier
Author-email: bussonniermatthias@gmail.com
Requires-Python: >3
Classifier: License :: OSI Approved :: MIT License
